README.md
setup.py
pulumi_equinix/__init__.py
pulumi_equinix/_enums.py
pulumi_equinix/_utilities.py
pulumi_equinix/provider.py
pulumi_equinix/pulumi-plugin.json
pulumi_equinix/py.typed
pulumi_equinix.egg-info/PKG-INFO
pulumi_equinix.egg-info/SOURCES.txt
pulumi_equinix.egg-info/dependency_links.txt
pulumi_equinix.egg-info/not-zip-safe
pulumi_equinix.egg-info/requires.txt
pulumi_equinix.egg-info/top_level.txt
pulumi_equinix/config/__init__.py
pulumi_equinix/config/__init__.pyi
pulumi_equinix/config/vars.py
pulumi_equinix/fabric/__init__.py
pulumi_equinix/fabric/_enums.py
pulumi_equinix/fabric/_inputs.py
pulumi_equinix/fabric/cloud_router.py
pulumi_equinix/fabric/connection.py
pulumi_equinix/fabric/connection_route_aggregation.py
pulumi_equinix/fabric/connection_route_filter.py
pulumi_equinix/fabric/get_cloud_router.py
pulumi_equinix/fabric/get_cloud_routers.py
pulumi_equinix/fabric/get_connection.py
pulumi_equinix/fabric/get_connection_route_aggregation.py
pulumi_equinix/fabric/get_connection_route_aggregations.py
pulumi_equinix/fabric/get_connection_route_filter.py
pulumi_equinix/fabric/get_connection_route_filters.py
pulumi_equinix/fabric/get_connections.py
pulumi_equinix/fabric/get_marketplace_subscription.py
pulumi_equinix/fabric/get_metro.py
pulumi_equinix/fabric/get_metros.py
pulumi_equinix/fabric/get_network.py
pulumi_equinix/fabric/get_networks.py
pulumi_equinix/fabric/get_port.py
pulumi_equinix/fabric/get_ports.py
pulumi_equinix/fabric/get_precision_time_service.py
pulumi_equinix/fabric/get_precision_time_services.py
pulumi_equinix/fabric/get_route_aggregation.py
pulumi_equinix/fabric/get_route_aggregation_rule.py
pulumi_equinix/fabric/get_route_aggregation_rules.py
pulumi_equinix/fabric/get_route_aggregations.py
pulumi_equinix/fabric/get_route_filter.py
pulumi_equinix/fabric/get_route_filter_rule.py
pulumi_equinix/fabric/get_route_filter_rules.py
pulumi_equinix/fabric/get_route_filters.py
pulumi_equinix/fabric/get_routing_protocol.py
pulumi_equinix/fabric/get_service_profile.py
pulumi_equinix/fabric/get_service_profiles.py
pulumi_equinix/fabric/get_service_token.py
pulumi_equinix/fabric/get_service_tokens.py
pulumi_equinix/fabric/get_stream.py
